NiukeWangCYuyanRumenZixueZhinan/README.md
NiukeWangCYuyanRumenZixueZhinan/__init__.py
NiukeWangCYuyanRumenZixueZhinan/__main__.py
NiukeWangCYuyanRumenZixueZhinan/file.epub
NiukeWangCYuyanRumenZixueZhinan/index.html
NiukeWangCYuyanRumenZixueZhinan/css/__init__.py
NiukeWangCYuyanRumenZixueZhinan/css/annotations.css
NiukeWangCYuyanRumenZixueZhinan/css/main.css
NiukeWangCYuyanRumenZixueZhinan/css/normalize.css
NiukeWangCYuyanRumenZixueZhinan/css/popup.css
NiukeWangCYuyanRumenZixueZhinan/font/__init__.py
NiukeWangCYuyanRumenZixueZhinan/font/fontello.eot
NiukeWangCYuyanRumenZixueZhinan/font/fontello.svg
NiukeWangCYuyanRumenZixueZhinan/font/fontello.ttf
NiukeWangCYuyanRumenZixueZhinan/font/fontello.woff
NiukeWangCYuyanRumenZixueZhinan/img/__init__.py
NiukeWangCYuyanRumenZixueZhinan/img/annotator-glyph-sprite.png
NiukeWangCYuyanRumenZixueZhinan/img/annotator-icon-sprite.png
NiukeWangCYuyanRumenZixueZhinan/img/apple-touch-icon.png
NiukeWangCYuyanRumenZixueZhinan/img/cancelfullscreen.png
NiukeWangCYuyanRumenZixueZhinan/img/close.png
NiukeWangCYuyanRumenZixueZhinan/img/fullscreen.png
NiukeWangCYuyanRumenZixueZhinan/img/loader.gif
NiukeWangCYuyanRumenZixueZhinan/img/menu-icon.png
NiukeWangCYuyanRumenZixueZhinan/img/save.png
NiukeWangCYuyanRumenZixueZhinan/img/saved.png
NiukeWangCYuyanRumenZixueZhinan/img/settings-s.png
NiukeWangCYuyanRumenZixueZhinan/img/settings.png
NiukeWangCYuyanRumenZixueZhinan/img/star.png
NiukeWangCYuyanRumenZixueZhinan/js/__init__.py
NiukeWangCYuyanRumenZixueZhinan/js/epub.js
NiukeWangCYuyanRumenZixueZhinan/js/epub.min.js
NiukeWangCYuyanRumenZixueZhinan/js/epub.min.map
NiukeWangCYuyanRumenZixueZhinan/js/hooks.min.js
NiukeWangCYuyanRumenZixueZhinan/js/hooks.min.map
NiukeWangCYuyanRumenZixueZhinan/js/reader.js
NiukeWangCYuyanRumenZixueZhinan/js/reader.js.map
NiukeWangCYuyanRumenZixueZhinan/js/reader.min.js
NiukeWangCYuyanRumenZixueZhinan/js/reader.min.map
NiukeWangCYuyanRumenZixueZhinan/js/hooks/__init__.py
niuke_wang_c_yuyan_rumen_zixue_zhinan-2024.3.5.0.dist-info/METADATA
niuke_wang_c_yuyan_rumen_zixue_zhinan-2024.3.5.0.dist-info/WHEEL
niuke_wang_c_yuyan_rumen_zixue_zhinan-2024.3.5.0.dist-info/entry_points.txt
niuke_wang_c_yuyan_rumen_zixue_zhinan-2024.3.5.0.dist-info/top_level.txt
niuke_wang_c_yuyan_rumen_zixue_zhinan-2024.3.5.0.dist-info/RECORD
